{
	"databaseOverhead": "5,34 MB",
	"postRevision": "538",
	"spamComments": "0",
	"pageLoad": "9.51",
	"pageSpeedScore": "94",
	"previous": [
		"Previous: A (94%) ",
		"Previous: B (81%) "
	],
	"slowScore": "81",
	"lasReport": " 03-July-2022, 09:18:17",
	"serverRegion": "Test server region: London, UK",
	"vunerabilityTotal": "Nessuna",
	"webTrust": "Clean",
	"malware": "Clean",
	"lastCheck": " 03-July-2022, 09:18:26",
	"previouspageLoad": "7.543",
	"pageSize": "2.68",
	"previouspageSize": "3.25",
	"requests": "6",
	"previousRequests": "59",
	"updateSummary": [
		"163",
		"Da 01/Gennaio/2022 a 1/Gennaio/2023"
	],
	"pluginsUpdated": "143",
	"themesUpdated": "19",
	"wpcoreUpdated": "1",
	"upTime": "99.594%",
	"responseTime": "3,04s",
	"downTime": "22",
	"downtimeDescription": "Downtime  ( 12 Hrs 33 Mins  )"
}